pylibcontainer/__init__.py
pylibcontainer/__main__.py
pylibcontainer/colorhelper.py
pylibcontainer/container.py
pylibcontainer/example.py
pylibcontainer/image.py
pylibcontainer/tar.py
pylibcontainer/trust.py
pylibcontainer/utils.py
pylibcontainer/trusted/keyring.gpg
pylibcontainer-0.0.6.dist-info/DESCRIPTION.rst
pylibcontainer-0.0.6.dist-info/METADATA
pylibcontainer-0.0.6.dist-info/RECORD
pylibcontainer-0.0.6.dist-info/WHEEL
pylibcontainer-0.0.6.dist-info/entry_points.txt
pylibcontainer-0.0.6.dist-info/metadata.json
pylibcontainer-0.0.6.dist-info/top_level.txt
