Metadata-Version: 2.0
Name: pylibcontainer
Version: 0.0.6
Summary: An OCI runtime specification implementation library
Home-page: https://github.com/joaompinto/pylibcontainer
Author: João Pinto
Author-email: lamego.pinto@gmail.com
License: Apache-2
Platform: UNKNOWN
Classifier: Development Status :: 1 - Planning
Classifier: Environment :: Console
Classifier: Intended Audience :: Developers
Classifier: Intended Audience :: Information Technology
Classifier: Intended Audience :: System Administrators
Classifier: License :: Freely Distributable
Classifier: License :: OSI Approved :: Apache Software License
Classifier: Operating System :: OS Independent
Classifier: Programming Language :: Python
Classifier: Programming Language :: Python :: 2.7
Classifier: Programming Language :: Python :: 3.4
Classifier: Topic :: Software Development :: Testing
Classifier: Topic :: Utilities
Requires-Dist: cgroupspy
Requires-Dist: click
Requires-Dist: clint
Requires-Dist: colorama
Requires-Dist: python
Requires-Dist: python-gnupg
Requires-Dist: requests
Requires-Dist: tmsyscall
